final_project_wanyingli/__init__.py
final_project_wanyingli/final_project_wanyingli.py
final_project_wanyingli-0.1.0.dist-info/LICENSE
final_project_wanyingli-0.1.0.dist-info/WHEEL
final_project_wanyingli-0.1.0.dist-info/METADATA
final_project_wanyingli-0.1.0.dist-info/RECORD
