Metadata-Version: 2.1
Name: final-project-wanyingli
Version: 0.1.0
Summary: Python package that returns the total country lending projects from the World Bank and the Asian Development Bank.
License: MIT
Author: Wanyingli
Author-email: wl2722@columbia.edu
Requires-Python: >=3.8,<4.0
Classifier: License :: OSI Approved :: MIT License
Classifier: Programming Language :: Python :: 3
Classifier: Programming Language :: Python :: 3.8
